azure/mgmt/containerinstance/__init__.py
azure/mgmt/containerinstance/_configuration.py
azure/mgmt/containerinstance/_container_instance_management_client.py
azure/mgmt/containerinstance/_patch.py
azure/mgmt/containerinstance/_serialization.py
azure/mgmt/containerinstance/_vendor.py
azure/mgmt/containerinstance/_version.py
azure/mgmt/containerinstance/py.typed
azure/mgmt/containerinstance/aio/__init__.py
azure/mgmt/containerinstance/aio/_configuration.py
azure/mgmt/containerinstance/aio/_container_instance_management_client.py
azure/mgmt/containerinstance/aio/_patch.py
azure/mgmt/containerinstance/aio/operations/__init__.py
azure/mgmt/containerinstance/aio/operations/_container_groups_operations.py
azure/mgmt/containerinstance/aio/operations/_containers_operations.py
azure/mgmt/containerinstance/aio/operations/_location_operations.py
azure/mgmt/containerinstance/aio/operations/_operations.py
azure/mgmt/containerinstance/aio/operations/_patch.py
azure/mgmt/containerinstance/aio/operations/_subnet_service_association_link_operations.py
azure/mgmt/containerinstance/models/__init__.py
azure/mgmt/containerinstance/models/_container_instance_management_client_enums.py
azure/mgmt/containerinstance/models/_models_py3.py
azure/mgmt/containerinstance/models/_patch.py
azure/mgmt/containerinstance/operations/__init__.py
azure/mgmt/containerinstance/operations/_container_groups_operations.py
azure/mgmt/containerinstance/operations/_containers_operations.py
azure/mgmt/containerinstance/operations/_location_operations.py
azure/mgmt/containerinstance/operations/_operations.py
azure/mgmt/containerinstance/operations/_patch.py
azure/mgmt/containerinstance/operations/_subnet_service_association_link_operations.py
azure_mgmt_containerinstance-10.1.0.dist-info/LICENSE
azure_mgmt_containerinstance-10.1.0.dist-info/METADATA
azure_mgmt_containerinstance-10.1.0.dist-info/WHEEL
azure_mgmt_containerinstance-10.1.0.dist-info/top_level.txt
azure_mgmt_containerinstance-10.1.0.dist-info/RECORD
